matrix_calculation_lib/__init__.py
matrix_calculation_lib/main.py
matrix_nararobo-0.0.2.dist-info/METADATA
matrix_nararobo-0.0.2.dist-info/WHEEL
matrix_nararobo-0.0.2.dist-info/top_level.txt
matrix_nararobo-0.0.2.dist-info/RECORD
