Metadata-Version: 2.1
Name: matrix-nararobo
Version: 0.0.2
Summary: A library that can calculate square matrices.
Home-page: UNKNOWN
Author: aoi
Author-email: UNKNOWN
License: UNKNOWN
Platform: UNKNOWN
